crypto/__init__.py
crypto/crypto.py
py_cryptocurrency-1.3.dist-info/METADATA
py_cryptocurrency-1.3.dist-info/WHEEL
py_cryptocurrency-1.3.dist-info/top_level.txt
py_cryptocurrency-1.3.dist-info/RECORD
