Metadata-Version: 2.1
Name: py-cryptocurrency
Version: 1.3
Summary: Wrapper to get real time cypto currency values
Home-page: https://github.com/AmarnathCJD/py-cryptocurrency
Author: AmarnathCJD
Author-email: AmarnathCJD@users.noreply.github.com
License: GNU
Download-URL: https://github.com/AmarnathCJD/py-cryptocurrency/releases/tag/1.3
Keywords: py,crypto,currency
Platform: UNKNOWN
Classifier: Development Status :: 5 - Production/Stable
Classifier: Intended Audience :: Developers
Classifier: Topic :: Education
Classifier: Programming Language :: Python :: 3.6
Classifier: Programming Language :: Python :: 3.9
Classifier: License :: OSI Approved :: GNU Lesser General Public License v3 or later (LGPLv3+)
Requires-Dist: requests
